.DS_Store
udiff/__init__.py
udiff/__version__.py
udiff/constants.py
udiff/errors.py
udiff/parser.py
udiff-0.1.0.dist-info/LICENSE
udiff-0.1.0.dist-info/METADATA
udiff-0.1.0.dist-info/WHEEL
udiff-0.1.0.dist-info/top_level.txt
udiff-0.1.0.dist-info/RECORD
